fluentCrawler/BaseModel.py
fluentCrawler/NewsModel.py
fluentCrawler/anno.py
fluentCrawler/joinUtil.py
fluentCrawler-1.0.1.dist-info/LICENSE
fluentCrawler-1.0.1.dist-info/METADATA
fluentCrawler-1.0.1.dist-info/WHEEL
fluentCrawler-1.0.1.dist-info/top_level.txt
fluentCrawler-1.0.1.dist-info/RECORD
