Metadata-Version: 2.1
Name: fluentCrawler
Version: 1.0.1
Summary: A decorator crawler
Home-page: https://gitee.com/szw1259577135/flu-crawler
Author: szw
Author-email: 1259577135@qq.com
License: UNKNOWN
Platform: all
Classifier: Programming Language :: Python :: 3
Classifier: License :: OSI Approved :: MIT License
Classifier: Operating System :: OS Independent
License-File: LICENSE
Requires-Dist: Django (>=1.1.1)
Requires-Dist: caldav (==0.1.4)
Requires-Dist: retrying (==1.3.3)
Requires-Dist: w3lib (==1.22.0)
Requires-Dist: requests (==2.25.1)
Requires-Dist: lxml (==4.6.3)
Requires-Dist: urllib3 (==1.26.4)
Requires-Dist: gne (==0.2.6)
Requires-Dist: gerapy-auto-extractor (==0.1.2)
